augmentations/__init__.py
augmentations/add_noise.py
augmentations/elastic_deformation.py
augmentations/flip.py
augmentations/gaussian_blur.py
augmentations/intensity_scaling.py
augmentations/occlusion.py
augmentations/random_crop_and_scale.py
augmentations/random_rotation.py
MedAugment-0.1.dist-info/LICENSE
MedAugment-0.1.dist-info/METADATA
MedAugment-0.1.dist-info/WHEEL
MedAugment-0.1.dist-info/top_level.txt
MedAugment-0.1.dist-info/RECORD
